date_formatter/__init__.py
date_formatter/date_formatter.py
date_formatter-0.1.1.dist-info/LICENSE
date_formatter-0.1.1.dist-info/WHEEL
date_formatter-0.1.1.dist-info/METADATA
date_formatter-0.1.1.dist-info/RECORD
