Metadata-Version: 2.1
Name: date-formatter
Version: 0.1.1
Summary: A Python package for formatting strings into readable date strings
Home-page: https://github.com/pauladjata/date_formatter.git
Keywords: text
Author: pauladjata
Author-email: info@adjata.com
Requires-Python: >=3.7
Classifier: Programming Language :: Python :: 3
Classifier: Programming Language :: Python :: 3.7
Classifier: Programming Language :: Python :: 3.8
Classifier: Programming Language :: Python :: 3.9
Project-URL: Repository, https://github.com/pauladjata/date_formatter.git
